{
    "type": "package",
    "package_attr_name": "adguardhome",
    "package_attr_set": "No package set",
    "package_pname": "adguardhome",
    "package_pversion": "0.107.52",
    "package_platforms": [
        "armv6l-linux",
        "aarch64-darwin",
        "i686-linux",
        "armv7l-linux",
        "x86_64-linux",
        "aarch64-linux",
        "x86_64-darwin"
    ],
    "package_outputs": [
        "out"
    ],
    "package_default_output": "out",
    "package_programs": [
        "adguardhome"
    ],
    "package_license": [
        {
            "url": "https://spdx.org/licenses/GPL-3.0-only.html",
            "fullName": "GNU General Public License v3.0 only"
        }
    ],
    "package_license_set": [
        "GNU General Public License v3.0 only"
    ],
    "package_maintainers": [
        {
            "name": "Sebastien Bariteau",
            "github": "numkem",
            "email": "numkem@numkem.org"
        },
        {
            "name": "Iago Manoel Brito",
            "github": "iagocq",
            "email": null
        },
        {
            "name": "Ryan Horiguchi",
            "github": "rhoriguchi",
            "email": "ryan.horiguchi@gmail.com"
        }
    ],
    "package_maintainers_set": [
        "Sebastien Bariteau",
        "Iago Manoel Brito",
        "Ryan Horiguchi"
    ],
    "package_description": "Network-wide ads & trackers blocking DNS server",
    "package_longDescription": null,
    "package_hydra": null,
    "package_system": "x86_64-linux",
    "package_homepage": [
        "https://github.com/AdguardTeam/AdGuardHome"
    ],
    "package_position": "pkgs/servers/adguardhome/default.nix:25"
}