{
    "type": "package",
    "package_attr_name": "haskellPackages.lvmlib",
    "package_attr_set": "haskellPackages",
    "package_pname": "lvmlib",
    "package_pversion": "1.1",
    "package_platforms": [
        "x86_64-redox",
        "armv7l-linux",
        "riscv64-none",
        "mipsel-netbsd",
        "armv6l-linux",
        "rx-none",
        "s390x-none",
        "i686-cygwin",
        "arm-none",
        "i686-linux",
        "mips-none",
        "x86_64-windows",
        "x86_64-cygwin",
        "powerpc-none",
        "x86_64-genode",
        "javascript-ghcjs",
        "riscv64-linux",
        "wasm32-wasi",
        "or1k-none",
        "armv6l-none",
        "riscv64-netbsd",
        "aarch64-none",
        "armv5tel-linux",
        "armv7l-netbsd",
        "armv6l-netbsd",
        "i686-freebsd",
        "x86_64-linux",
        "armv7a-netbsd",
        "aarch64-netbsd",
        "aarch64-darwin",
        "s390x-linux",
        "armv7a-darwin",
        "m68k-none",
        "mipsel-linux",
        "i686-windows",
        "wasm64-wasi",
        "s390-linux",
        "armv7a-linux",
        "powerpc64-linux",
        "mips64el-linux",
        "loongarch64-linux",
        "i686-openbsd",
        "powerpc64le-linux",
        "msp430-none",
        "m68k-netbsd",
        "x86_64-darwin",
        "x86_64-none",
        "mmix-mmixware",
        "x86_64-solaris",
        "mips64-none",
        "riscv32-linux",
        "mips64-linux",
        "i686-darwin",
        "microblaze-none",
        "riscv32-netbsd",
        "x86_64-freebsd",
        "mips-linux",
        "microblazeel-linux",
        "i686-none",
        "microblaze-linux",
        "i686-netbsd",
        "microblazeel-none",
        "x86_64-openbsd",
        "aarch64-linux",
        "x86_64-netbsd",
        "i686-genode",
        "aarch64_be-none",
        "aarch64-genode",
        "powerpc-netbsd",
        "avr-none",
        "s390-none",
        "m68k-linux",
        "powerpcle-none",
        "vc4-none",
        "riscv32-none"
    ],
    "package_outputs": [
        "doc",
        "out"
    ],
    "package_default_output": "out",
    "package_programs": [],
    "package_license": [
        {
            "url": "https://spdx.org/licenses/BSD-3-Clause.html",
            "fullName": "BSD 3-clause \"New\" or \"Revised\" License"
        }
    ],
    "package_license_set": [
        "BSD 3-clause \"New\" or \"Revised\" License"
    ],
    "package_maintainers": [],
    "package_maintainers_set": [],
    "package_description": "The Lazy Virtual Machine (LVM)",
    "package_longDescription": null,
    "package_hydra": null,
    "package_system": "x86_64-linux",
    "package_homepage": [
        "https://hackage.haskell.org/package/lvmlib"
    ],
    "package_position": "pkgs/development/haskell-modules/hackage-packages.nix:198128"
}