{
    "type": "package",
    "package_attr_name": "woodpecker-server",
    "package_attr_set": "No package set",
    "package_pname": "woodpecker-server",
    "package_pversion": "2.7.0",
    "package_platforms": [
        "armv5tel-linux",
        "mips64el-linux",
        "powerpc64-linux",
        "s390-linux",
        "armv7a-darwin",
        "x86_64-linux",
        "aarch64-darwin",
        "microblaze-linux",
        "loongarch64-linux",
        "armv7a-linux",
        "i686-freebsd",
        "armv6l-linux",
        "wasm32-wasi",
        "wasm64-wasi",
        "s390x-linux",
        "microblazeel-linux",
        "aarch64-linux",
        "powerpc64le-linux",
        "riscv64-linux",
        "mips64-linux",
        "i686-darwin",
        "x86_64-darwin",
        "armv7l-linux",
        "m68k-linux",
        "mips-linux",
        "mipsel-linux",
        "i686-linux",
        "riscv32-linux",
        "x86_64-freebsd"
    ],
    "package_outputs": [
        "out"
    ],
    "package_default_output": "out",
    "package_programs": [
        "woodpecker-server"
    ],
    "package_license": [
        {
            "url": "https://spdx.org/licenses/Apache-2.0.html",
            "fullName": "Apache License 2.0"
        }
    ],
    "package_license_set": [
        "Apache License 2.0"
    ],
    "package_maintainers": [
        {
            "name": "Bruno BELANYI",
            "github": "ambroisie",
            "email": "bruno.nixpkgs@belanyi.fr"
        },
        {
            "name": "techknowlogick",
            "github": "techknowlogick",
            "email": "techknowlogick@gitea.com"
        },
        {
            "name": "Adam C. Stephens",
            "github": "adamcstephens",
            "email": "happy.plan4249@valkor.net"
        }
    ],
    "package_maintainers_set": [
        "Bruno BELANYI",
        "techknowlogick",
        "Adam C. Stephens"
    ],
    "package_description": "Woodpecker Continuous Integration server",
    "package_longDescription": null,
    "package_hydra": null,
    "package_system": "x86_64-linux",
    "package_homepage": [
        "https://woodpecker-ci.org/"
    ],
    "package_position": "pkgs/development/tools/continuous-integration/woodpecker/server.nix:18"
}